sha_all_original_p.v
module sha256_H_0(
          output [255:0] H_0
          );

      assign H_0 = {
          32'h6A09E667, 32'hBB67AE85, 32'h3C6EF372, 32'hA54FF53A,
          32'h510E527F, 32'h9B05688C, 32'h1F83D9AB, 32'h5BE0CD19
      };

endmodule

module sha256_K_machine (
          input clk,
          input rst,
          input en,
          output [31:0] K
          );

      reg [2047:0] rom_q;
      wire [2047:0] rom_d = {rom_q[2015:0], rom_q[2047:2016]};
      assign K = rom_q[2047:2016];

      always @(posedge clk)
      begin
          if (rst) begin
              rom_q <= {
                  32'h428a2f98, 32'h71374491, 32'hb5c0fbcf, 32'he9b5dba5,
                  32'h3956c25b, 32'h59f111f1, 32'h923f82a4, 32'hab1c5ed5,
                  32'hd807aa98, 32'h12835b01, 32'h243185be, 32'h550c7dc3,
                  32'h72be5d74, 32'h80deb1fe, 32'h9bdc06a7, 32'hc19bf174,
                  32'he49b69c1, 32'hefbe4786, 32'h0fc19dc6, 32'h240ca1cc,
                  32'h2de92c6f, 32'h4a7484aa, 32'h5cb0a9dc, 32'h76f988da,
                  32'h983e5152, 32'ha831c66d, 32'hb00327c8, 32'hbf597fc7,
                  32'hc6e00bf3, 32'hd5a79147, 32'h06ca6351, 32'h14292967,
                  32'h27b70a85, 32'h2e1b2138, 32'h4d2c6dfc, 32'h53380d13,
                  32'h650a7354, 32'h766a0abb, 32'h81c2c92e, 32'h92722c85,
                  32'ha2bfe8a1, 32'ha81a664b, 32'hc24b8b70, 32'hc76c51a3,
                  32'hd192e819, 32'hd6990624, 32'hf40e3585, 32'h106aa070,
                  32'h19a4c116, 32'h1e376c08, 32'h2748774c, 32'h34b0bcb5,
                  32'h391c0cb3, 32'h4ed8aa4a, 32'h5b9cca4f, 32'h682e6ff3,
                  32'h748f82ee, 32'h78a5636f, 32'h84c87814, 32'h8cc70208,
                  32'h90befffa, 32'ha4506ceb, 32'hbef9a3f7, 32'hc67178f2
              };
          end else if (en) begin
              rom_q <= rom_d;
          end
      end
endmodule

module sha256_s0 (
          input wire [31:0] x,
          output wire [31:0] s0
          );

      assign s0 = ({x[6:0], x[31:7]} ^ {x[17:0], x[31:18]} ^ (x >> 3));

endmodule
module sha256_s1 (
          input wire [31:0] x,
          output wire [31:0] s1
          );

      assign s1 = ({x[16:0], x[31:17]} ^ {x[18:0], x[31:19]} ^ (x >> 10));

      endmodule
module W_machine #(parameter WORDSIZE=1) (
          input clk,
          input [WORDSIZE*16-1:0] M,
          input M_valid,
          output [WORDSIZE-1:0] W_tm2, W_tm15,
          input [WORDSIZE-1:0] s1_Wtm2, s0_Wtm15,
          output [WORDSIZE-1:0] W
          );

      assign W_tm2 = W_stack_q[WORDSIZE*2-1:WORDSIZE*1];
      assign W_tm15 = W_stack_q[WORDSIZE*15-1:WORDSIZE*14];
      wire [WORDSIZE-1:0] W_tm7 = W_stack_q[WORDSIZE*7-1:WORDSIZE*6];
      wire [WORDSIZE-1:0] W_tm16 = W_stack_q[WORDSIZE*16-1:WORDSIZE*15];
      wire [WORDSIZE-1:0] Wt_next = s1_Wtm2 + W_tm7 + s0_Wtm15 + W_tm16;

      reg [WORDSIZE*16-1:0] W_stack_q;
      wire [WORDSIZE*16-1:0] W_stack_d = {W_stack_q[WORDSIZE*15-1:0], Wt_next};
      assign W = W_stack_q[WORDSIZE*16-1:WORDSIZE*15];

      always @(posedge clk)
      begin
          if (M_valid) begin
              W_stack_q <= M;
          end else begin
              W_stack_q <= W_stack_d;
          end
      end

      endmodule

module sha256_S1 (
          input wire [31:0] x,
          output wire [31:0] S1
          );

      assign S1 = ({x[5:0], x[31:6]} ^ {x[10:0], x[31:11]} ^ {x[24:0], x[31:25]});
      endmodule

module Ch #(parameter WORDSIZE=0) (
          input wire [WORDSIZE-1:0] x, y, z,
          output wire [WORDSIZE-1:0] Ch
          );

      assign Ch = ((x & y) ^ (~x & z));
      endmodule

module sha256_S0 (
          input wire [31:0] x,
          output wire [31:0] S0
          );

      assign S0 = ({x[1:0], x[31:2]} ^ {x[12:0], x[31:13]} ^ {x[21:0], x[31:22]});
      endmodule

module Maj #(parameter WORDSIZE=0) (
          input wire [WORDSIZE-1:0] x, y, z,
          output wire [WORDSIZE-1:0] Maj
          );

      assign Maj = (x & y) ^ (x & z) ^ (y & z);
      endmodule

module sha2_round #(parameter WORDSIZE=0) (
          input clk,
          input [WORDSIZE-1:0] Kj, Wj,
          input [WORDSIZE-1:0] a_in, b_in, c_in, d_in, e_in, f_in, g_in, h_in,
          input [WORDSIZE-1:0] Ch_e_f_g, Maj_a_b_c, S0_a, S1_e,
          output [WORDSIZE-1:0] a_out, b_out, c_out, d_out, e_out, f_out, g_out, h_out
          );

    // Stage 1 registers
    reg [WORDSIZE-1:0] T1_partial_q1, T2_q1, Kj_q, Wj_q;
    reg [WORDSIZE-1:0] a_q1, b_q1, c_q1, d_q1, e_q1, f_q1, g_q1;

    // Stage 2 registers
    reg [WORDSIZE-1:0] T1_q2, T2_q2;
    reg [WORDSIZE-1:0] a_q2, b_q2, c_q2, d_q2, e_q2, f_q2, g_q2;

    always @(posedge clk) begin
        // Stage 1: compute partial T1 and T2
        T1_partial_q1 <= h_in + S1_e + Ch_e_f_g;
        T2_q1         <= S0_a + Maj_a_b_c;
        Kj_q <= Kj; Wj_q <= Wj;
        a_q1 <= a_in; b_q1 <= b_in; c_q1 <= c_in; d_q1 <= d_in;
        e_q1 <= e_in; f_q1 <= f_in; g_q1 <= g_in;

        // Stage 2: finish T1
        T1_q2 <= T1_partial_q1 + Kj_q + Wj_q;
        T2_q2 <= T2_q1;
        a_q2 <= a_q1; b_q2 <= b_q1; c_q2 <= c_q1; d_q2 <= d_q1;
        e_q2 <= e_q1; f_q2 <= f_q1; g_q2 <= g_q1;
    end

    // Stage 3: final outputs (combinational)
    assign a_out = T1_q2 + T2_q2;
    assign b_out = a_q2;
    assign c_out = b_q2;
    assign d_out = c_q2;
    assign e_out = d_q2 + T1_q2;
    assign f_out = e_q2;
    assign g_out = f_q2;
    assign h_out = g_q2;
    endmodule

module sha256_round (
          input clk,
          input [31:0] Kj, Wj,
          input [31:0] a_in, b_in, c_in, d_in, e_in, f_in, g_in, h_in,
          output [31:0] a_out, b_out, c_out, d_out, e_out, f_out, g_out, h_out
          );

      wire [31:0] Ch_e_f_g, Maj_a_b_c, S0_a, S1_e;

      Ch #(.WORDSIZE(32)) Ch (
          .x(e_in), .y(f_in), .z(g_in), .Ch(Ch_e_f_g)
      );

      Maj #(.WORDSIZE(32)) Maj (
          .x(a_in), .y(b_in), .z(c_in), .Maj(Maj_a_b_c)
      );

      sha256_S0 S0 (
          .x(a_in), .S0(S0_a)
      );

      sha256_S1 S1 (
          .x(e_in), .S1(S1_e)
      );

      sha2_round #(.WORDSIZE(32)) sha256_round_inner (
          .clk(clk), .Kj(Kj), .Wj(Wj),
          .a_in(a_in), .b_in(b_in), .c_in(c_in), .d_in(d_in),
          .e_in(e_in), .f_in(f_in), .g_in(g_in), .h_in(h_in),
          .Ch_e_f_g(Ch_e_f_g), .Maj_a_b_c(Maj_a_b_c), .S0_a(S0_a), .S1_e(S1_e),
          .a_out(a_out), .b_out(b_out), .c_out(c_out), .d_out(d_out),
          .e_out(e_out), .f_out(f_out), .g_out(g_out), .h_out(h_out)
      );

      endmodule

module sha256_block (
          input clk, rst,
          input [255:0] H_in,
          input [511:0] M_in,
          input input_valid,
          output [255:0] H_out,
          output output_valid
          );

      reg [6:0] round;
      wire [31:0] a_in = H_in[255:224], b_in = H_in[223:192];
      wire [31:0] c_in = H_in[191:160], d_in = H_in[159:128];
      wire [31:0] e_in = H_in[127:96],  f_in = H_in[95:64];
      wire [31:0] g_in = H_in[63:32],   h_in = H_in[31:0];

      reg [31:0] a_q, b_q, c_q, d_q, e_q, f_q, g_q, h_q;
      wire [31:0] a_d, b_d, c_d, d_d, e_d, f_d, g_d, h_d;
      wire [31:0] W_tm2, W_tm15, s1_Wtm2, s0_Wtm15, Wj, Kj;

      reg [1:0] stall;

      // Forwarding: use a_d directly when pipeline is running (stall==0)
      // During stall, hold a_q steady so pipeline fills with correct values
      wire [31:0] a_next = (stall > 0) ? a_q : a_d;
      wire [31:0] b_next = (stall > 0) ? b_q : b_d;
      wire [31:0] c_next = (stall > 0) ? c_q : c_d;
      wire [31:0] d_next = (stall > 0) ? d_q : d_d;
      wire [31:0] e_next = (stall > 0) ? e_q : e_d;
      wire [31:0] f_next = (stall > 0) ? f_q : f_d;
      wire [31:0] g_next = (stall > 0) ? g_q : g_d;
      wire [31:0] h_next = (stall > 0) ? h_q : h_d;

      assign H_out = {
          a_in + a_q, b_in + b_q, c_in + c_q, d_in + d_q,
          e_in + e_q, f_in + f_q, g_in + g_q, h_in + h_q
      };
      assign output_valid = round == 64;

      always @(posedge clk)
      begin
          if (rst) begin
              round <= 0;
              stall <= 2;
          end else if (input_valid) begin
              a_q <= a_in; b_q <= b_in; c_q <= c_in; d_q <= d_in;
              e_q <= e_in; f_q <= f_in; g_q <= g_in; h_q <= h_in;
              round <= 0;
              stall <= 2;        // hold for 2 cycles to fill pipeline
          end else if (stall > 0) begin
              stall <= stall - 1; // pipeline filling, don't update a_q or round
          end else begin
              a_q <= a_d; b_q <= b_d; c_q <= c_d; d_q <= d_d;
              e_q <= e_d; f_q <= f_d; g_q <= g_d; h_q <= h_d;
              round <= round + 1;
          end
      end

      // Feed forwarded values into round function
      sha256_round sha256_round (
          .clk(clk), .Kj(Kj), .Wj(Wj),
          .a_in(a_next), .b_in(b_next), .c_in(c_next), .d_in(d_next),
          .e_in(e_next), .f_in(f_next), .g_in(g_next), .h_in(h_next),
          .a_out(a_d), .b_out(b_d), .c_out(c_d), .d_out(d_d),
          .e_out(e_d), .f_out(f_d), .g_out(g_d), .h_out(h_d)
      );

      sha256_s0 sha256_s0 (.x(W_tm15), .s0(s0_Wtm15));
      sha256_s1 sha256_s1 (.x(W_tm2),  .s1(s1_Wtm2));

      W_machine #(.WORDSIZE(32)) W_machine (
          .clk(clk),
          .M(M_in), .M_valid(input_valid),
          .W_tm2(W_tm2), .W_tm15(W_tm15),
          .s1_Wtm2(s1_Wtm2), .s0_Wtm15(s0_Wtm15),
          .W(Wj)
      );

      // K machine gated with stall==0 so K stays in sync with rounds
      sha256_K_machine sha256_K_machine (
          .clk(clk), .rst(input_valid), .en(stall == 0), .K(Kj)
      );

      endmodule

module sha256_top (
    input clk,
    input rst,
    input start,
    input [511:0] block,
    output [255:0] hash,
    output done
);

    wire [255:0] H0;

    sha256_H_0 H_init (
        .H_0(H0)
    );

    sha256_block dut (
        .clk(clk),
        .rst(rst),
        .H_in(H0),
        .M_in(block),
        .input_valid(start),
        .H_out(hash),
        .output_valid(done)
    );

endmodule

tb_sha256.v
`timescale 1ns/1ps

module tb_sha256;

    reg clk;
    reg rst;
    reg start;
    reg [511:0] block;

    wire [255:0] hash;
    wire done;

    sha256_top dut (
        .clk(clk),
        .rst(rst),
        .start(start),
        .block(block),
        .hash(hash),
        .done(done)
    );

    always #5 clk = ~clk;

    initial begin
        $dumpfile("sha256.vcd");
        $dumpvars(0, tb_sha256);
        clk   = 0;
        rst   = 1;
        start = 0;
        block = 512'd0;

        #20 rst = 0;

        // SHA256("abc") — single-line message block
        block = 512'h61626380000000000000000000000000000000000000000000000000000000000000000000000000000000000000000000000000000000000000000000000018;

        #10 start = 1;
        #10 start = 0;

        @(posedge done);
        #1;
        $display("SHA256 = %h", hash);
        $finish;
    end

endmodule

sha256.vcd
$date
	Sun Mar 08 01:29:16 2026
$end
$version
	Icarus Verilog
$end
$timescale
	1ps
$end
$scope module tb_sha256 $end
$var wire 256 ! hash [255:0] $end
$var wire 1 " done $end
$var reg 512 # block [511:0] $end
$var reg 1 $ clk $end
$var reg 1 % rst $end
$var reg 1 & start $end
$scope module dut $end
$var wire 256 ' H0 [255:0] $end
$var wire 512 ( block [511:0] $end
$var wire 1 $ clk $end
$var wire 1 % rst $end
$var wire 1 & start $end
$var wire 256 ) hash [255:0] $end
$var wire 1 " done $end
$scope module H_init $end
$var wire 256 * H_0 [255:0] $end
$upscope $end
$scope module dut $end
$var wire 256 + H_in [255:0] $end
$var wire 512 , M_in [511:0] $end
$var wire 1 $ clk $end
$var wire 1 & input_valid $end
$var wire 1 % rst $end
$var wire 32 - s1_Wtm2 [31:0] $end
$var wire 32 . s0_Wtm15 [31:0] $end
$var wire 1 " output_valid $end
$var wire 32 / h_next [31:0] $end
$var wire 32 0 h_in [31:0] $end
$var wire 32 1 h_d [31:0] $end
$var wire 32 2 g_next [31:0] $end
$var wire 32 3 g_in [31:0] $end
$var wire 32 4 g_d [31:0] $end
$var wire 32 5 f_next [31:0] $end
$var wire 32 6 f_in [31:0] $end
$var wire 32 7 f_d [31:0] $end
$var wire 32 8 e_next [31:0] $end
$var wire 32 9 e_in [31:0] $end
$var wire 32 : e_d [31:0] $end
$var wire 32 ; d_next [31:0] $end
$var wire 32 < d_in [31:0] $end
$var wire 32 = d_d [31:0] $end
$var wire 32 > c_next [31:0] $end
$var wire 32 ? c_in [31:0] $end
$var wire 32 @ c_d [31:0] $end
$var wire 32 A b_next [31:0] $end
$var wire 32 B b_in [31:0] $end
$var wire 32 C b_d [31:0] $end
$var wire 32 D a_next [31:0] $end
$var wire 32 E a_in [31:0] $end
$var wire 32 F a_d [31:0] $end
$var wire 32 G Wj [31:0] $end
$var wire 32 H W_tm2 [31:0] $end
$var wire 32 I W_tm15 [31:0] $end
$var wire 32 J Kj [31:0] $end
$var wire 256 K H_out [255:0] $end
$var reg 32 L a_q [31:0] $end
$var reg 32 M b_q [31:0] $end
$var reg 32 N c_q [31:0] $end
$var reg 32 O d_q [31:0] $end
$var reg 32 P e_q [31:0] $end
$var reg 32 Q f_q [31:0] $end
$var reg 32 R g_q [31:0] $end
$var reg 32 S h_q [31:0] $end
$var reg 7 T round [6:0] $end
$var reg 2 U stall [1:0] $end
$scope module W_machine $end
$var wire 512 V M [511:0] $end
$var wire 1 & M_valid $end
$var wire 1 $ clk $end
$var wire 32 W s1_Wtm2 [31:0] $end
$var wire 32 X s0_Wtm15 [31:0] $end
$var wire 32 Y Wt_next [31:0] $end
$var wire 32 Z W_tm7 [31:0] $end
$var wire 32 [ W_tm2 [31:0] $end
$var wire 32 \ W_tm16 [31:0] $end
$var wire 32 ] W_tm15 [31:0] $end
$var wire 512 ^ W_stack_d [511:0] $end
$var wire 32 _ W [31:0] $end
$var parameter 32 ` WORDSIZE $end
$var reg 512 a W_stack_q [511:0] $end
$upscope $end
$scope module sha256_K_machine $end
$var wire 1 $ clk $end
$var wire 1 b en $end
$var wire 1 & rst $end
$var wire 2048 c rom_d [2047:0] $end
$var wire 32 d K [31:0] $end
$var reg 2048 e rom_q [2047:0] $end
$upscope $end
$scope module sha256_round $end
$var wire 32 f Kj [31:0] $end
$var wire 32 g Wj [31:0] $end
$var wire 32 h a_in [31:0] $end
$var wire 32 i b_in [31:0] $end
$var wire 32 j c_in [31:0] $end
$var wire 1 $ clk $end
$var wire 32 k d_in [31:0] $end
$var wire 32 l e_in [31:0] $end
$var wire 32 m f_in [31:0] $end
$var wire 32 n g_in [31:0] $end
$var wire 32 o h_in [31:0] $end
$var wire 32 p h_out [31:0] $end
$var wire 32 q g_out [31:0] $end
$var wire 32 r f_out [31:0] $end
$var wire 32 s e_out [31:0] $end
$var wire 32 t d_out [31:0] $end
$var wire 32 u c_out [31:0] $end
$var wire 32 v b_out [31:0] $end
$var wire 32 w a_out [31:0] $end
$var wire 32 x S1_e [31:0] $end
$var wire 32 y S0_a [31:0] $end
$var wire 32 z Maj_a_b_c [31:0] $end
$var wire 32 { Ch_e_f_g [31:0] $end
$scope module Ch $end
$var wire 32 | Ch [31:0] $end
$var wire 32 } x [31:0] $end
$var wire 32 ~ y [31:0] $end
$var wire 32 !" z [31:0] $end
$var parameter 32 "" WORDSIZE $end
$upscope $end
$scope module Maj $end
$var wire 32 #" Maj [31:0] $end
$var wire 32 $" x [31:0] $end
$var wire 32 %" y [31:0] $end
$var wire 32 &" z [31:0] $end
$var parameter 32 '" WORDSIZE $end
$upscope $end
$scope module S0 $end
$var wire 32 (" S0 [31:0] $end
$var wire 32 )" x [31:0] $end
$upscope $end
$scope module S1 $end
$var wire 32 *" S1 [31:0] $end
$var wire 32 +" x [31:0] $end
$upscope $end
$scope module sha256_round_inner $end
$var wire 32 ," Ch_e_f_g [31:0] $end
$var wire 32 -" Kj [31:0] $end
$var wire 32 ." Maj_a_b_c [31:0] $end
$var wire 32 /" S0_a [31:0] $end
$var wire 32 0" S1_e [31:0] $end
$var wire 32 1" Wj [31:0] $end
$var wire 32 2" a_in [31:0] $end
$var wire 32 3" b_in [31:0] $end
$var wire 32 4" b_out [31:0] $end
$var wire 32 5" c_in [31:0] $end
$var wire 32 6" c_out [31:0] $end
$var wire 1 $ clk $end
$var wire 32 7" d_in [31:0] $end
$var wire 32 8" d_out [31:0] $end
$var wire 32 9" e_in [31:0] $end
$var wire 32 :" f_in [31:0] $end
$var wire 32 ;" f_out [31:0] $end
$var wire 32 <" g_in [31:0] $end
$var wire 32 =" g_out [31:0] $end
$var wire 32 >" h_in [31:0] $end
$var wire 32 ?" h_out [31:0] $end
$var wire 32 @" e_out [31:0] $end
$var wire 32 A" a_out [31:0] $end
$var parameter 32 B" WORDSIZE $end
$var reg 32 C" Kj_q [31:0] $end
$var reg 32 D" T1_partial_q1 [31:0] $end
$var reg 32 E" T1_q2 [31:0] $end
$var reg 32 F" T2_q1 [31:0] $end
$var reg 32 G" T2_q2 [31:0] $end
$var reg 32 H" Wj_q [31:0] $end
$var reg 32 I" a_q1 [31:0] $end
$var reg 32 J" a_q2 [31:0] $end
$var reg 32 K" b_q1 [31:0] $end
$var reg 32 L" b_q2 [31:0] $end
$var reg 32 M" c_q1 [31:0] $end
$var reg 32 N" c_q2 [31:0] $end
$var reg 32 O" d_q1 [31:0] $end
$var reg 32 P" d_q2 [31:0] $end
$var reg 32 Q" e_q1 [31:0] $end
$var reg 32 R" e_q2 [31:0] $end
$var reg 32 S" f_q1 [31:0] $end
$var reg 32 T" f_q2 [31:0] $end
$var reg 32 U" g_q1 [31:0] $end
$var reg 32 V" g_q2 [31:0] $end
$upscope $end
$upscope $end
$scope module sha256_s0 $end
$var wire 32 W" s0 [31:0] $end
$var wire 32 X" x [31:0] $end
$upscope $end
$scope module sha256_s1 $end
$var wire 32 Y" s1 [31:0] $end
$var wire 32 Z" x [31:0] $end
$upscope $end
$upscope $end
$upscope $end
$upscope $end
$enddefinitions $end
$comment Show the parameter values. $end
$dumpall
b100000 B"
b100000 '"
b100000 ""
b100000 `
$end
#0
$dumpvars
bx Z"
bx Y"
bx X"
bx W"
bx V"
bx U"
bx T"
bx S"
bx R"
bx Q"
bx P"
bx O"
bx N"
bx M"
bx L"
bx K"
bx J"
bx I"
bx H"
bx G"
bx F"
bx E"
bx D"
bx C"
bx A"
bx @"
bx ?"
bx >"
bx ="
bx <"
bx ;"
bx :"
bx 9"
bx 8"
bx 7"
bx 6"
bx 5"
bx 4"
bx 3"
bx 2"
bx 1"
bx 0"
bx /"
bx ."
bx -"
bx ,"
bx +"
bx *"
bx )"
bx ("
bx &"
bx %"
bx $"
bx #"
bx !"
bx ~
bx }
bx |
bx {
bx z
bx y
bx x
bx w
bx v
bx u
bx t
bx s
bx r
bx q
bx p
bx o
bx n
bx m
bx l
bx k
bx j
bx i
bx h
bx g
bx f
bx e
bx d
bx c
xb
bx a
bx _
bx ^
bx ]
bx \
bx [
bx Z
bx Y
bx X
bx W
b0 V
bx U
bx T
bx S
bx R
bx Q
bx P
bx O
bx N
bx M
bx L
bx K
bx J
bx I
bx H
bx G
bx F
b1101010000010011110011001100111 E
bx D
bx C
b10111011011001111010111010000101 B
bx A
bx @
b111100011011101111001101110010 ?
bx >
bx =
b10100101010011111111010100111010 <
bx ;
bx :
b1010001000011100101001001111111 9
bx 8
bx 7
b10011011000001010110100010001100 6
bx 5
bx 4
b11111100000111101100110101011 3
bx 2
bx 1
b1011011111000001100110100011001 0
bx /
bx .
bx -
b0 ,
b110101000001001111001100110011110111011011001111010111010000101001111000110111011110011011100101010010101001111111101010011101001010001000011100101001001111111100110110000010101101000100011000001111110000011110110011010101101011011111000001100110100011001 +
b110101000001001111001100110011110111011011001111010111010000101001111000110111011110011011100101010010101001111111101010011101001010001000011100101001001111111100110110000010101101000100011000001111110000011110110011010101101011011111000001100110100011001 *
bx )
b0 (
b110101000001001111001100110011110111011011001111010111010000101001111000110111011110011011100101010010101001111111101010011101001010001000011100101001001111111100110110000010101101000100011000001111110000011110110011010101101011011111000001100110100011001 '
0&
1%
0$
b0 #
x"
bx !
$end
#5000
0b
b10 U
0"
b0 T
1$
#10000
0$
#15000
1$
#20000
0$
b1100001011000100110001110000000000000000000000000000000000000000000000000000000000000000000000000000000000000000000000000000000000000000000000000000000000000000000000000000000000000000000000000000000000000000000000000000000000000000000000000000000000000000000000000000000000000000000000000000000000000000000000000000000000000000000000000000000000000000000000000000000000000000000000000000000000000000000000000000000000000000000000000000000000000000000000000000000000000000000000000000000000000000000000000011000 #
b1100001011000100110001110000000000000000000000000000000000000000000000000000000000000000000000000000000000000000000000000000000000000000000000000000000000000000000000000000000000000000000000000000000000000000000000000000000000000000000000000000000000000000000000000000000000000000000000000000000000000000000000000000000000000000000000000000000000000000000000000000000000000000000000000000000000000000000000000000000000000000000000000000000000000000000000000000000000000000000000000000000000000000000000000011000 (
b1100001011000100110001110000000000000000000000000000000000000000000000000000000000000000000000000000000000000000000000000000000000000000000000000000000000000000000000000000000000000000000000000000000000000000000000000000000000000000000000000000000000000000000000000000000000000000000000000000000000000000000000000000000000000000000000000000000000000000000000000000000000000000000000000000000000000000000000000000000000000000000000000000000000000000000000000000000000000000000000000000000000000000000000000011000 ,
b1100001011000100110001110000000000000000000000000000000000000000000000000000000000000000000000000000000000000000000000000000000000000000000000000000000000000000000000000000000000000000000000000000000000000000000000000000000000000000000000000000000000000000000000000000000000000000000000000000000000000000000000000000000000000000000000000000000000000000000000000000000000000000000000000000000000000000000000000000000000000000000000000000000000000000000000000000000000000000000000000000000000000000000000000011000 V
0%
#25000
b1 U
1$
#30000
0$
1&
#35000
b110101100001110010011100101011 x
b110101100001110010011100101011 *"
b110101100001110010011100101011 0"
b11001110001000001011010001111110 y
b11001110001000001011010001111110 ("
b11001110001000001011010001111110 /"
b1100001011000100110001110000000 Y
b0 -
b0 W
b0 Y"
b0 .
b0 X
b0 W"
b11111100001011100100110001100 {
b11111100001011100100110001100 |
b11111100001011100100110001100 ,"
b111010011011111110011001100111 z
b111010011011111110011001100111 #"
b111010011011111110011001100111 ."
b1011011111000001100110100011001 /
b1011011111000001100110100011001 o
b1011011111000001100110100011001 >"
b11111100000111101100110101011 2
b11111100000111101100110101011 n
b11111100000111101100110101011 !"
b11111100000111101100110101011 <"
b10011011000001010110100010001100 5
b10011011000001010110100010001100 m
b10011011000001010110100010001100 ~
b10011011000001010110100010001100 :"
b1010001000011100101001001111111 8
b1010001000011100101001001111111 l
b1010001000011100101001001111111 }
b1010001000011100101001001111111 +"
b1010001000011100101001001111111 9"
b10100101010011111111010100111010 ;
b10100101010011111111010100111010 k
b10100101010011111111010100111010 7"
b111100011011101111001101110010 >
b111100011011101111001101110010 j
b111100011011101111001101110010 &"
b111100011011101111001101110010 5"
b10111011011001111010111010000101 A
b10111011011001111010111010000101 i
b10111011011001111010111010000101 %"
b10111011011001111010111010000101 3"
b1101010000010011110011001100111 D
b1101010000010011110011001100111 h
b1101010000010011110011001100111 $"
b1101010000010011110011001100111 )"
b1101010000010011110011001100111 2"
b1110001001101110100010010010001101101011100000011111011110011111110100110110101110110111010010100111001010101101100001001011011010110011111000100010001111100011001001000111111100000101010010010101011000111000101111011010101110110000000011110101010100110000001001010000011010110110000000100100100001100011000010110111110010101010000110001111101110000110111001010111110010111010111010010000000110111101011000111111110100110111101110000000110101001111100000110011011111100010111010011100100100110110110100111000001111011111011111001000111100001100000111111000001100111011100011000100100000011001010000111001100001011011110100100101100011011110100101001110100100001001010101001011100101100001010100111011100011101101111100110001000110110101001100000111110010100010101001010101000001100011100011001101101101100000000001100100111110010001011111101011001011111111100011111000110111000000000101111110011110101011010011110010001010001110000011011001010011000110101000100010100001010010010100101100111001001111011011100001010100001010010111000011011001000010011100001001101001011000110110111111100010100110011100000001101000100110110010100001010011100110101010001110110011010100000101010111011100000011100001011001001001011101001001001110010001011001000010110100010101111111110100010100001101010000001101001100110010010111100001001001011100010110111000011000111011011000101000110100011110100011001001011101000000110011101011010011001000001100010010011110100000011100011010110000101000100000110101010100000011100000001100110100100110000010001011000011110001101110110110000001000001001110100100001110111010011000011010010110000101111001011010100111001000111000000110010110011010011101101100010101010010010100101101110011100110010100100111101101000001011100110111111110011011101001000111110000010111011100111100010100101011000110110111110000100110010000111100000010100100011001100011100000010000010001001000010111110111111111111101010100100010100000110110011101011101111101111100110100011111101111100011001110001011110001111001001000010100010100010111110011000 c
b1000010100010100010111110011000 J
b1000010100010100010111110011000 d
b1000010100010100010111110011000 f
b1000010100010100010111110011000 -"
b0 H
b0 [
b0 Z"
b0 I
b0 ]
b0 X"
b0 Z
b1100001011000100110001110000000 \
b1100001100001011000100110001110000000 ^
b1100001011000100110001110000000 G
b1100001011000100110001110000000 _
b1100001011000100110001110000000 g
b1100001011000100110001110000000 1"
b10 U
b1011011111000001100110100011001 S
b11111100000111101100110101011 R
b10011011000001010110100010001100 Q
b1010001000011100101001001111111 P
b10100101010011111111010100111010 O
b111100011011101111001101110010 N
b10111011011001111010111010000101 M
b1101010000010011110011001100111001110110110011110101110100001010011110001101110111100110111001000100101010011111111010100111010010100010000111001010010011111110001101100000101011010001000110000011111100000111101100110101011010110111110000011001101000110010 !
b1101010000010011110011001100111001110110110011110101110100001010011110001101110111100110111001000100101010011111111010100111010010100010000111001010010011111110001101100000101011010001000110000011111100000111101100110101011010110111110000011001101000110010 )
b1101010000010011110011001100111001110110110011110101110100001010011110001101110111100110111001000100101010011111111010100111010010100010000111001010010011111110001101100000101011010001000110000011111100000111101100110101011010110111110000011001101000110010 K
b1101010000010011110011001100111 L
b1000010100010100010111110011000011100010011011101000100100100011011010111000000111110111100111111101001101101011101101110100101001110010101011011000010010110110101100111110001000100011111000110010010001111111000001010100100101010110001110001011110110101011101100000000111101010101001100000010010100000110101101100000001001001000011000110000101101111100101010100001100011111011100001101110010101111100101110101110100100000001101111010110001111111101001101111011100000001101010011111000001100110111111000101110100111001001001101101101001110000011110111110111110010001111000011000001111110000011001110111000110001001000000110010100001110011000010110111101001001011000110111101001010011101001000010010101010010111001011000010101001110111000111011011111001100010001101101010011000001111100101000101010010101010000011000111000110011011011011000000000011001001111100100010111111010110010111111111000111110001101110000000001011111100111101010110100111100100010100011100000110110010100110001101010001000101000010100100101001011001110010011110110111000010101000010100101110000110110010000100111000010011010010110001101101111111000101001100111000000011010001001101100101000010100111001101010100011101100110101000001010101110111000000111000010110010010010111010010010011100100010110010000101101000101011111111101000101000011010100000011010011001100100101111000010010010111000101101110000110001110110110001010001101000111101000110010010111010000001100111010110100110010000011000100100111101000000111000110101100001010001000001101010101000000111000000011001101001001100000100010110000111100011011101101100000010000010011101001000011101110100110000110100101100001011110010110101001110010001110000001100101100110100111011011000101010100100101001011011100111001100101001001111011010000010111001101111111100110111010010001111100000101110111001111000101001010110001101101111100001001100100001111000000101001000110011000111000000100000100010010000101111101111111111111010101001000101000001101100111010111011111011111001101000111111011111000110011100010111100011110010 e
b1100001011000100110001110000000000000000000000000000000000000000000000000000000000000000000000000000000000000000000000000000000000000000000000000000000000000000000000000000000000000000000000000000000000000000000000000000000000000000000000000000000000000000000000000000000000000000000000000000000000000000000000000000000000000000000000000000000000000000000000000000000000000000000000000000000000000000000000000000000000000000000000000000000000000000000000000000000000000000000000000000000000000000000000000011000 a
1$
#40000
0$
0&
#45000
b11110000000000000000 -
b11110000000000000000 W
b11110000000000000000 Y"
b11000 H
b11000 [
b11000 Z"
b11110000000000000000 Y
b0 \
b110000110000101100010011000111000000000000000000011110000000000000000 ^
b0 G
b0 _
b0 g
b0 1"
b11111100000111101100110101011 U"
b10011011000001010110100010001100 S"
b1010001000011100101001001111111 Q"
b10100101010011111111010100111010 O"
b111100011011101111001101110010 M"
b10111011011001111010111010000101 K"
b1101010000010011110011001100111 I"
b1100001011000100110001110000000 H"
b1000010100010100010111110011000 C"
b1000100100001001101011100101 F"
b10110000111011011011110111010000 D"
b1100001100001011000100110001110000000 a
b1 U
1$
#50000
0$
